deepboard/__init__.py
deepboard/__version__.py
deepboard/gui/THEME.yml
deepboard/gui/__init__.py
deepboard/gui/entry.py
deepboard/gui/main.py
deepboard/gui/requirements.txt
deepboard/gui/utils.py
deepboard/gui/assets/artefacts.css
deepboard/gui/assets/base.css
deepboard/gui/assets/base.js
deepboard/gui/assets/charts.css
deepboard/gui/assets/compare.css
deepboard/gui/assets/datagrid.css
deepboard/gui/assets/fileview.css
deepboard/gui/assets/image_viewer.js
deepboard/gui/assets/right_panel.css
deepboard/gui/assets/theme.css
deepboard/gui/components/__init__.py
deepboard/gui/components/artefactFilter.py
deepboard/gui/components/artefact_group.py
deepboard/gui/components/artefact_header.py
deepboard/gui/components/autocomplete.py
deepboard/gui/components/chart_type.py
deepboard/gui/components/legend.py
deepboard/gui/components/log_selector.py
deepboard/gui/components/modal.py
deepboard/gui/components/plotly2fh.py
deepboard/gui/components/quick_filter.py
deepboard/gui/components/smoother.py
deepboard/gui/components/split_selector.py
deepboard/gui/components/stat_cell.py
deepboard/gui/components/stat_line.py
deepboard/gui/pages/__init__.py
deepboard/gui/pages/not_found.py
deepboard/gui/pages/compare_page/__init__.py
deepboard/gui/pages/compare_page/compare_page.py
deepboard/gui/pages/compare_page/routes.py
deepboard/gui/pages/compare_page/components/__init__.py
deepboard/gui/pages/compare_page/components/card_list.py
deepboard/gui/pages/compare_page/components/chart.py
deepboard/gui/pages/compare_page/components/compare_setup.py
deepboard/gui/pages/compare_page/components/split_card.py
deepboard/gui/pages/compare_page/components/utils.py
deepboard/gui/pages/main_page/__init__.py
deepboard/gui/pages/main_page/handlers.py
deepboard/gui/pages/main_page/main_page.py
deepboard/gui/pages/main_page/routes.py
deepboard/gui/pages/main_page/datagrid/__init__.py
deepboard/gui/pages/main_page/datagrid/compare_button.py
deepboard/gui/pages/main_page/datagrid/datagrid.py
deepboard-0.3.0.dist-info/METADATA
deepboard-0.3.0.dist-info/WHEEL
deepboard-0.3.0.dist-info/entry_points.txt
deepboard-0.3.0.dist-info/RECORD
