Metadata-Version: 2.4
Name: deepboard
Version: 0.3.0
Summary: Organize your research project like a pro with Deepboard
Project-URL: Homepage, https://github.com/anthol42/deepboard
Project-URL: Issues, https://github.com/anthol42/deepboard/issues
Author-email: Anthony Lavertu <alavertu2@gmail.com>
Keywords: board,deep,deepboard,jax,pytorch,tensorboard,tensorflow,torch
Classifier: Development Status :: 4 - Beta
Classifier: Intended Audience :: Education
Classifier: Intended Audience :: Science/Research
Classifier: Operating System :: MacOS
Classifier: Operating System :: POSIX :: Linux
Classifier: Programming Language :: Python :: 3
Classifier: Topic :: Scientific/Engineering :: Artificial Intelligence
Requires-Python: >=3.10
Requires-Dist: matplotlib
Requires-Dist: pandas
Requires-Dist: pillow
Requires-Dist: python-fasthtml>=0.12.33
Provides-Extra: full
Requires-Dist: fh-plotly; extra == 'full'
Requires-Dist: markupsafe; extra == 'full'
Requires-Dist: python-fasthtml; extra == 'full'
